setup.py
yandex_yaca_parser/__init__.py
yandex_yaca_parser/exceptions.py
yandex_yaca_parser/utils.py
yandex_yaca_parser.egg-info/PKG-INFO
yandex_yaca_parser.egg-info/SOURCES.txt
yandex_yaca_parser.egg-info/dependency_links.txt
yandex_yaca_parser.egg-info/top_level.txt