Metadata-Version: 1.1
Name: yandex-yaca-parser
Version: 0.0.2
Summary: Parse yandex yaca. See https://yandex.ru/yaca/?text=test
Home-page: https://github.com/KokocGroup/yandex-yaca-parser
Author: UNKNOWN
Author-email: UNKNOWN
License: UNKNOWN
Download-URL: https://github.com/KokocGroup/yandex-yaca-parser/tarball/v0.0.2
Platform: UNKNOWN
